{
  "label": "boat",
  "landmarks": [
    {
      "x": 22.033215,
      "y": 20.593505,
      "z": -3.720455,
      "visibility": 0.999112
    },
    {
      "x": 22.671859,
      "y": 20.239668,
      "z": -4.846993,
      "visibility": 0.99913
    },
    {
      "x": 22.770385,
      "y": 20.2807,
      "z": -4.84796,
      "visibility": 0.999166
    },
    {
      "x": 22.880505,
      "y": 20.329732,
      "z": -4.847275,
      "visibility": 0.999295
    },
    {
      "x": 22.608005,
      "y": 20.184436,
      "z": -2.939879,
      "visibility": 0.999096
    },
    {
      "x": 22.663022,
      "y": 20.185376,
      "z": -2.940776,
      "visibility": 0.99912
    },
    {
      "x": 22.720539,
      "y": 20.186578,
      "z": -2.942157,
      "visibility": 0.999166
    },
    {
      "x": 23.619667,
      "y": 21.043235,
      "z": -7.701904,
      "visibility": 0.999067
    },
    {
      "x": 23.495014,
      "y": 20.855881,
      "z": 0.840199,
      "visibility": 0.998607
    },
    {
      "x": 22.104739,
      "y": 21.267932,
      "z": -4.632079,
      "visibility": 0.999513
    },
    {
      "x": 21.974397,
      "y": 21.213607,
      "z": -2.146303,
      "visibility": 0.999005
    },
    {
      "x": 22.824245,
      "y": 24.655756,
      "z": -12.508265,
      "visibility": 0.999803
    },
    {
      "x": 22.093931,
      "y": 23.972644,
      "z": 6.858346,
      "visibility": 0.999426
    },
    {
      "x": 18.115276,
      "y": 25.511,
      "z": -14.751845,
      "visibility": 0.976681
    },
    {
      "x": 17.581175,
      "y": 25.185015,
      "z": 8.32871,
      "visibility": 0.131613
    },
    {
      "x": 13.65938,
      "y": 24.427824,
      "z": -11.50682,
      "visibility": 0.91484
    },
    {
      "x": 13.62204,
      "y": 24.405717,
      "z": 4.00786,
      "visibility": 0.088712
    },
    {
      "x": 12.344594,
      "y": 24.742238,
      "z": -13.086975,
      "visibility": 0.872916
    },
    {
      "x": 12.137222,
      "y": 24.570484,
      "z": 4.109978,
      "visibility": 0.079707
    },
    {
      "x": 12.238861,
      "y": 24.079263,
      "z": -12.400946,
      "visibility": 0.876259
    },
    {
      "x": 12.149611,
      "y": 24.178667,
      "z": 2.369015,
      "visibility": 0.083164
    },
    {
      "x": 12.553029,
      "y": 23.934635,
      "z": -11.135283,
      "visibility": 0.824401
    },
    {
      "x": 12.525506,
      "y": 24.071343,
      "z": 3.098358,
      "visibility": 0.086108
    },
    {
      "x": 17.682016,
      "y": 30.673217,
      "z": -5.728555,
      "visibility": 0.987987
    },
    {
      "x": 17.417593,
      "y": 29.880098,
      "z": 5.749413,
      "visibility": 0.987123
    },
    {
      "x": 12.904057,
      "y": 24.8475,
      "z": -3.66627,
      "visibility": 0.861434
    },
    {
      "x": 12.894985,
      "y": 24.699628,
      "z": 6.001151,
      "visibility": 0.1553
    },
    {
      "x": 8.350388,
      "y": 19.728589,
      "z": -0.775066,
      "visibility": 0.948582
    },
    {
      "x": 8.547181,
      "y": 19.807021,
      "z": 9.435988,
      "visibility": 0.218415
    },
    {
      "x": 7.256678,
      "y": 19.452685,
      "z": -0.634033,
      "visibility": 0.936859
    },
    {
      "x": 7.421173,
      "y": 19.487023,
      "z": 9.606151,
      "visibility": 0.265288
    },
    {
      "x": 8.896435,
      "y": 16.503048,
      "z": -5.130544,
      "visibility": 0.952451
    },
    {
      "x": 9.141741,
      "y": 16.64743,
      "z": 6.449717,
      "visibility": 0.293537
    }
  ]
}