{
  "label": "bridge",
  "landmarks": [
    {
      "x": 13.75078,
      "y": 8.444861,
      "z": 0.095484,
      "visibility": 0.99989
    },
    {
      "x": 14.032225,
      "y": 8.708199,
      "z": -0.37032,
      "visibility": 0.999902
    },
    {
      "x": 14.045564,
      "y": 8.806648,
      "z": -0.369467,
      "visibility": 0.999944
    },
    {
      "x": 14.062389,
      "y": 8.921137,
      "z": -0.371025,
      "visibility": 0.999918
    },
    {
      "x": 14.016501,
      "y": 8.620827,
      "z": 0.431844,
      "visibility": 0.999752
    },
    {
      "x": 14.016781,
      "y": 8.651811,
      "z": 0.433299,
      "visibility": 0.999787
    },
    {
      "x": 14.018997,
      "y": 8.70025,
      "z": 0.434122,
      "visibility": 0.999744
    },
    {
      "x": 14.054067,
      "y": 9.798112,
      "z": -1.71785,
      "visibility": 0.999965
    },
    {
      "x": 14.005658,
      "y": 9.587476,
      "z": 1.929699,
      "visibility": 0.999837
    },
    {
      "x": 13.476556,
      "y": 8.713831,
      "z": -0.316107,
      "visibility": 0.999893
    },
    {
      "x": 13.44838,
      "y": 8.604983,
      "z": 0.729416,
      "visibility": 0.999619
    },
    {
      "x": 12.181926,
      "y": 10.813353,
      "z": -3.702566,
      "visibility": 0.999999
    },
    {
      "x": 12.186121,
      "y": 9.813361,
      "z": 3.962379,
      "visibility": 0.999053
    },
    {
      "x": 9.349737,
      "y": 11.594809,
      "z": -4.157373,
      "visibility": 0.999676
    },
    {
      "x": 9.662943,
      "y": 10.541954,
      "z": 5.044585,
      "visibility": 0.381795
    },
    {
      "x": 6.862203,
      "y": 11.535034,
      "z": -4.285512,
      "visibility": 0.999523
    },
    {
      "x": 7.649994,
      "y": 10.396859,
      "z": 4.575112,
      "visibility": 0.720202
    },
    {
      "x": 6.241326,
      "y": 11.560479,
      "z": -5.004216,
      "visibility": 0.998363
    },
    {
      "x": 7.099782,
      "y": 10.319993,
      "z": 4.620393,
      "visibility": 0.687601
    },
    {
      "x": 6.321732,
      "y": 10.993803,
      "z": -4.818658,
      "visibility": 0.99815
    },
    {
      "x": 6.707405,
      "y": 10.410698,
      "z": 3.999931,
      "visibility": 0.681488
    },
    {
      "x": 6.520174,
      "y": 10.901,
      "z": -4.165581,
      "visibility": 0.997693
    },
    {
      "x": 7.022769,
      "y": 10.248686,
      "z": 4.268647,
      "visibility": 0.656084
    },
    {
      "x": 8.346857,
      "y": 5.813623,
      "z": -2.588297,
      "visibility": 0.99988
    },
    {
      "x": 8.464961,
      "y": 5.223161,
      "z": 2.584034,
      "visibility": 0.999503
    },
    {
      "x": 4.263389,
      "y": 3.813773,
      "z": -3.681037,
      "visibility": 0.924646
    },
    {
      "x": 4.457751,
      "y": 3.711776,
      "z": 1.88993,
      "visibility": 0.176359
    },
    {
      "x": 3.311065,
      "y": 10.430629,
      "z": -1.539349,
      "visibility": 0.866031
    },
    {
      "x": 3.736722,
      "y": 8.689699,
      "z": 4.486731,
      "visibility": 0.227392
    },
    {
      "x": 3.373108,
      "y": 11.415371,
      "z": -1.366503,
      "visibility": 0.892951
    },
    {
      "x": 3.855791,
      "y": 9.565964,
      "z": 4.70328,
      "visibility": 0.336438
    },
    {
      "x": 1.876973,
      "y": 11.098717,
      "z": -2.313511,
      "visibility": 0.906604
    },
    {
      "x": 2.426218,
      "y": 9.188911,
      "z": 3.602438,
      "visibility": 0.488335
    }
  ]
}