{
  "label": "cat-cow",
  "landmarks": [
    {
      "x": 1.735955,
      "y": 5.065213,
      "z": -2.033396,
      "visibility": 0.999986
    },
    {
      "x": 2.549405,
      "y": 4.461869,
      "z": -3.361952,
      "visibility": 0.999986
    },
    {
      "x": 2.699259,
      "y": 4.491197,
      "z": -3.365421,
      "visibility": 0.999986
    },
    {
      "x": 2.853369,
      "y": 4.520059,
      "z": -3.366178,
      "visibility": 0.999987
    },
    {
      "x": 2.519975,
      "y": 4.407864,
      "z": -1.343259,
      "visibility": 0.999974
    },
    {
      "x": 2.636904,
      "y": 4.39232,
      "z": -1.340044,
      "visibility": 0.999979
    },
    {
      "x": 2.769493,
      "y": 4.376134,
      "z": -1.333792,
      "visibility": 0.99999
    },
    {
      "x": 3.666728,
      "y": 5.411922,
      "z": -6.131012,
      "visibility": 0.999974
    },
    {
      "x": 3.598482,
      "y": 5.241887,
      "z": 2.64977,
      "visibility": 0.999995
    },
    {
      "x": 2.00096,
      "y": 6.479642,
      "z": -2.934289,
      "visibility": 0.999974
    },
    {
      "x": 1.937587,
      "y": 6.360887,
      "z": -0.349485,
      "visibility": 0.999962
    },
    {
      "x": 5.149498,
      "y": 12.427029,
      "z": -10.817426,
      "visibility": 0.999981
    },
    {
      "x": 5.989283,
      "y": 11.884111,
      "z": 8.6538,
      "visibility": 0.999839
    },
    {
      "x": 4.171378,
      "y": 23.576742,
      "z": -10.62325,
      "visibility": 0.987381
    },
    {
      "x": 5.307706,
      "y": 21.881673,
      "z": 9.748852,
      "visibility": 0.294749
    },
    {
      "x": 2.933145,
      "y": 33.56284,
      "z": -9.007979,
      "visibility": 0.986554
    },
    {
      "x": 4.130699,
      "y": 30.363094,
      "z": 9.452727,
      "visibility": 0.327921
    },
    {
      "x": 1.490914,
      "y": 34.234829,
      "z": -11.764211,
      "visibility": 0.986765
    },
    {
      "x": 3.047914,
      "y": 30.454387,
      "z": 10.376273,
      "visibility": 0.355544
    },
    {
      "x": 1.38922,
      "y": 33.55955,
      "z": -9.327417,
      "visibility": 0.984771
    },
    {
      "x": 2.835299,
      "y": 30.884951,
      "z": 7.547881,
      "visibility": 0.357356
    },
    {
      "x": 1.943274,
      "y": 33.442648,
      "z": -8.16697,
      "visibility": 0.979428
    },
    {
      "x": 3.307065,
      "y": 31.131729,
      "z": 8.302686,
      "visibility": 0.366217
    },
    {
      "x": 17.102441,
      "y": 17.959938,
      "z": -6.753032,
      "visibility": 0.999975
    },
    {
      "x": 16.945136,
      "y": 17.5427,
      "z": 6.768195,
      "visibility": 0.999915
    },
    {
      "x": 18.835528,
      "y": 32.56316,
      "z": -9.580753,
      "visibility": 0.995667
    },
    {
      "x": 18.445204,
      "y": 30.367407,
      "z": 5.515348,
      "visibility": 0.269198
    },
    {
      "x": 28.763286,
      "y": 31.330342,
      "z": -5.777484,
      "visibility": 0.994561
    },
    {
      "x": 26.829217,
      "y": 29.760891,
      "z": 12.352228,
      "visibility": 0.487632
    },
    {
      "x": 29.610358,
      "y": 29.372661,
      "z": -5.047091,
      "visibility": 0.993088
    },
    {
      "x": 27.824871,
      "y": 28.214936,
      "z": 13.134004,
      "visibility": 0.541146
    },
    {
      "x": 32.987303,
      "y": 33.402927,
      "z": -4.337838,
      "visibility": 0.991462
    },
    {
      "x": 30.321061,
      "y": 31.2105,
      "z": 12.36171,
      "visibility": 0.643076
    }
  ]
}