{
  "label": "chair",
  "landmarks": [
    {
      "x": 2.086673,
      "y": 1.835112,
      "z": -4.743764,
      "visibility": 0.99687
    },
    {
      "x": 2.19682,
      "y": 1.72533,
      "z": -4.718974,
      "visibility": 0.996688
    },
    {
      "x": 2.262478,
      "y": 1.717974,
      "z": -4.720606,
      "visibility": 0.997083
    },
    {
      "x": 2.332175,
      "y": 1.710144,
      "z": -4.723441,
      "visibility": 0.997334
    },
    {
      "x": 2.053306,
      "y": 1.737621,
      "z": -4.27759,
      "visibility": 0.995865
    },
    {
      "x": 2.019544,
      "y": 1.739984,
      "z": -4.277741,
      "visibility": 0.993864
    },
    {
      "x": 1.991588,
      "y": 1.741648,
      "z": -4.279183,
      "visibility": 0.993822
    },
    {
      "x": 2.529596,
      "y": 1.724362,
      "z": -4.09127,
      "visibility": 0.996748
    },
    {
      "x": 2.152977,
      "y": 1.759422,
      "z": -2.055885,
      "visibility": 0.993495
    },
    {
      "x": 2.281841,
      "y": 1.910176,
      "z": -4.458853,
      "visibility": 0.988717
    },
    {
      "x": 2.081885,
      "y": 1.921568,
      "z": -3.875799,
      "visibility": 0.985299
    },
    {
      "x": 3.114836,
      "y": 2.117979,
      "z": -4.717866,
      "visibility": 0.996442
    },
    {
      "x": 2.117921,
      "y": 2.196475,
      "z": -0.390923,
      "visibility": 0.987035
    },
    {
      "x": 2.842159,
      "y": 1.341705,
      "z": -7.315142,
      "visibility": 0.997293
    },
    {
      "x": 1.695725,
      "y": 1.560817,
      "z": 0.174435,
      "visibility": 0.725777
    },
    {
      "x": 2.809648,
      "y": 0.576507,
      "z": -8.168476,
      "visibility": 0.986928
    },
    {
      "x": 1.548462,
      "y": 0.838208,
      "z": -1.293123,
      "visibility": 0.866155
    },
    {
      "x": 2.804586,
      "y": 0.342608,
      "z": -8.96583,
      "visibility": 0.97294
    },
    {
      "x": 1.544489,
      "y": 0.665761,
      "z": -1.735622,
      "visibility": 0.821308
    },
    {
      "x": 2.764579,
      "y": 0.309103,
      "z": -8.770796,
      "visibility": 0.969625
    },
    {
      "x": 1.599479,
      "y": 0.638472,
      "z": -1.913837,
      "visibility": 0.81641
    },
    {
      "x": 2.726581,
      "y": 0.394362,
      "z": -8.170904,
      "visibility": 0.962575
    },
    {
      "x": 1.648656,
      "y": 0.67948,
      "z": -1.502612,
      "visibility": 0.830326
    },
    {
      "x": 3.464944,
      "y": 3.550934,
      "z": -1.549271,
      "visibility": 0.999079
    },
    {
      "x": 2.71516,
      "y": 3.574549,
      "z": 1.550966,
      "visibility": 0.997994
    },
    {
      "x": 2.611854,
      "y": 4.405683,
      "z": -2.851388,
      "visibility": 0.970844
    },
    {
      "x": 2.248342,
      "y": 4.393861,
      "z": -0.2008,
      "visibility": 0.820102
    },
    {
      "x": 3.299233,
      "y": 5.177993,
      "z": -0.009371,
      "visibility": 0.937859
    },
    {
      "x": 3.029967,
      "y": 5.148762,
      "z": 2.759549,
      "visibility": 0.69833
    },
    {
      "x": 3.515233,
      "y": 5.269596,
      "z": 0.195191,
      "visibility": 0.882886
    },
    {
      "x": 3.200239,
      "y": 5.247128,
      "z": 2.985432,
      "visibility": 0.662864
    },
    {
      "x": 2.635925,
      "y": 5.437417,
      "z": -1.371996,
      "visibility": 0.912666
    },
    {
      "x": 2.47109,
      "y": 5.418623,
      "z": 1.707998,
      "visibility": 0.709432
    }
  ]
}