{
  "label": "downward_dog",
  "landmarks": [
    {
      "x": 10.676697,
      "y": 16.186053,
      "z": -0.297228,
      "visibility": 0.999813
    },
    {
      "x": 10.150368,
      "y": 16.415056,
      "z": -0.96365,
      "visibility": 0.999867
    },
    {
      "x": 10.084145,
      "y": 16.333805,
      "z": -0.963748,
      "visibility": 0.999882
    },
    {
      "x": 10.015089,
      "y": 16.236837,
      "z": -0.96441,
      "visibility": 0.999887
    },
    {
      "x": 10.176366,
      "y": 16.442107,
      "z": -0.006834,
      "visibility": 0.999887
    },
    {
      "x": 10.129161,
      "y": 16.396575,
      "z": -0.006978,
      "visibility": 0.999887
    },
    {
      "x": 10.07859,
      "y": 16.346101,
      "z": -0.007254,
      "visibility": 0.999874
    },
    {
      "x": 9.632245,
      "y": 15.237117,
      "z": -3.01566,
      "visibility": 0.999774
    },
    {
      "x": 9.795202,
      "y": 15.469948,
      "z": 1.477871,
      "visibility": 0.999817
    },
    {
      "x": 10.764408,
      "y": 15.428469,
      "z": -0.862987,
      "visibility": 0.999623
    },
    {
      "x": 10.835149,
      "y": 15.491,
      "z": 0.441084,
      "visibility": 0.999457
    },
    {
      "x": 9.952829,
      "y": 12.129877,
      "z": -3.813627,
      "visibility": 0.999217
    },
    {
      "x": 10.500485,
      "y": 12.966581,
      "z": 2.830313,
      "visibility": 0.996808
    },
    {
      "x": 7.768933,
      "y": 16.394692,
      "z": -8.240096,
      "visibility": 0.986494
    },
    {
      "x": 9.059301,
      "y": 16.911881,
      "z": 5.313983,
      "visibility": 0.251265
    },
    {
      "x": 4.934001,
      "y": 20.083194,
      "z": -7.423399,
      "visibility": 0.969017
    },
    {
      "x": 6.509293,
      "y": 19.110854,
      "z": 1.993098,
      "visibility": 0.438008
    },
    {
      "x": 4.081497,
      "y": 20.354778,
      "z": -8.429528,
      "visibility": 0.958267
    },
    {
      "x": 5.835691,
      "y": 20.003518,
      "z": 1.969163,
      "visibility": 0.604307
    },
    {
      "x": 3.928014,
      "y": 20.173658,
      "z": -7.528932,
      "visibility": 0.950519
    },
    {
      "x": 5.223082,
      "y": 19.311895,
      "z": 0.929763,
      "visibility": 0.6121
    },
    {
      "x": 4.203168,
      "y": 20.176964,
      "z": -7.087666,
      "visibility": 0.939789
    },
    {
      "x": 5.578127,
      "y": 19.374856,
      "z": 1.524374,
      "visibility": 0.616102
    },
    {
      "x": 15.502513,
      "y": 4.245447,
      "z": -3.073535,
      "visibility": 0.997839
    },
    {
      "x": 15.458165,
      "y": 5.538495,
      "z": 3.084861,
      "visibility": 0.996906
    },
    {
      "x": 18.837586,
      "y": 11.806388,
      "z": -2.650679,
      "visibility": 0.980671
    },
    {
      "x": 18.263183,
      "y": 12.314967,
      "z": 3.071774,
      "visibility": 0.317174
    },
    {
      "x": 22.026576,
      "y": 18.662822,
      "z": -2.931078,
      "visibility": 0.983976
    },
    {
      "x": 21.321267,
      "y": 17.805471,
      "z": 4.196817,
      "visibility": 0.501577
    },
    {
      "x": 22.992533,
      "y": 19.975904,
      "z": -3.162119,
      "visibility": 0.981659
    },
    {
      "x": 22.301222,
      "y": 19.277748,
      "z": 4.183747,
      "visibility": 0.543792
    },
    {
      "x": 19.980282,
      "y": 21.017392,
      "z": -5.910173,
      "visibility": 0.977311
    },
    {
      "x": 19.402684,
      "y": 20.604623,
      "z": 2.633099,
      "visibility": 0.64829
    }
  ]
}