{
  "label": "goddess",
  "landmarks": [
    {
      "x": 3.298547,
      "y": 1.908971,
      "z": -2.022808,
      "visibility": 0.999998
    },
    {
      "x": 3.358072,
      "y": 1.82149,
      "z": -1.74243,
      "visibility": 0.999997
    },
    {
      "x": 3.391961,
      "y": 1.819828,
      "z": -1.742092,
      "visibility": 0.999994
    },
    {
      "x": 3.419214,
      "y": 1.821764,
      "z": -1.742957,
      "visibility": 0.999995
    },
    {
      "x": 3.245423,
      "y": 1.827136,
      "z": -1.731412,
      "visibility": 0.999997
    },
    {
      "x": 3.204091,
      "y": 1.830119,
      "z": -1.731785,
      "visibility": 0.999996
    },
    {
      "x": 3.168755,
      "y": 1.832968,
      "z": -1.731568,
      "visibility": 0.999997
    },
    {
      "x": 3.461932,
      "y": 1.870012,
      "z": -0.531082,
      "visibility": 0.999992
    },
    {
      "x": 3.121578,
      "y": 1.878439,
      "z": -0.463955,
      "visibility": 0.999998
    },
    {
      "x": 3.368368,
      "y": 2.009551,
      "z": -1.612994,
      "visibility": 0.999995
    },
    {
      "x": 3.233356,
      "y": 2.00525,
      "z": -1.597607,
      "visibility": 0.999997
    },
    {
      "x": 3.777803,
      "y": 2.467311,
      "z": 0.032008,
      "visibility": 0.999388
    },
    {
      "x": 2.777827,
      "y": 2.474247,
      "z": 0.007158,
      "visibility": 0.999813
    },
    {
      "x": 4.495913,
      "y": 2.658121,
      "z": -1.247647,
      "visibility": 0.998162
    },
    {
      "x": 2.06899,
      "y": 2.58704,
      "z": -1.086565,
      "visibility": 0.999463
    },
    {
      "x": 4.475529,
      "y": 1.985405,
      "z": -2.776433,
      "visibility": 0.994252
    },
    {
      "x": 2.107731,
      "y": 1.920801,
      "z": -2.425281,
      "visibility": 0.997889
    },
    {
      "x": 4.471957,
      "y": 1.807843,
      "z": -3.071306,
      "visibility": 0.971232
    },
    {
      "x": 2.09891,
      "y": 1.730105,
      "z": -2.753875,
      "visibility": 0.984004
    },
    {
      "x": 4.393918,
      "y": 1.792105,
      "z": -2.845669,
      "visibility": 0.965458
    },
    {
      "x": 2.18037,
      "y": 1.723053,
      "z": -2.534082,
      "visibility": 0.979472
    },
    {
      "x": 4.366602,
      "y": 1.865196,
      "z": -2.731953,
      "visibility": 0.950471
    },
    {
      "x": 2.214496,
      "y": 1.791108,
      "z": -2.391881,
      "visibility": 0.97379
    },
    {
      "x": 3.590779,
      "y": 3.756698,
      "z": -0.031618,
      "visibility": 0.999395
    },
    {
      "x": 2.96473,
      "y": 3.745449,
      "z": 0.030458,
      "visibility": 0.999744
    },
    {
      "x": 4.50075,
      "y": 4.096252,
      "z": -2.349944,
      "visibility": 0.995036
    },
    {
      "x": 2.032328,
      "y": 4.065455,
      "z": -2.208624,
      "visibility": 0.998098
    },
    {
      "x": 4.410907,
      "y": 5.028154,
      "z": 0.303625,
      "visibility": 0.987977
    },
    {
      "x": 2.133229,
      "y": 5.01893,
      "z": 0.267941,
      "visibility": 0.997278
    },
    {
      "x": 4.316155,
      "y": 5.169796,
      "z": 0.535565,
      "visibility": 0.973005
    },
    {
      "x": 2.248638,
      "y": 5.175196,
      "z": 0.484813,
      "visibility": 0.990285
    },
    {
      "x": 4.779614,
      "y": 5.305798,
      "z": -0.350357,
      "visibility": 0.964887
    },
    {
      "x": 1.784839,
      "y": 5.262961,
      "z": -0.372005,
      "visibility": 0.984688
    }
  ]
}