{
  "label": "lotus",
  "landmarks": [
    {
      "x": 3.424502,
      "y": 1.073987,
      "z": -1.310823,
      "visibility": 0.999942
    },
    {
      "x": 3.559459,
      "y": 0.935367,
      "z": -1.359388,
      "visibility": 0.999976
    },
    {
      "x": 3.610514,
      "y": 0.939189,
      "z": -1.359413,
      "visibility": 0.999965
    },
    {
      "x": 3.672764,
      "y": 0.942552,
      "z": -1.359436,
      "visibility": 0.999977
    },
    {
      "x": 3.485823,
      "y": 0.924166,
      "z": -1.035919,
      "visibility": 0.999972
    },
    {
      "x": 3.475913,
      "y": 0.921094,
      "z": -1.036094,
      "visibility": 0.999964
    },
    {
      "x": 3.465887,
      "y": 0.917015,
      "z": -1.037822,
      "visibility": 0.999978
    },
    {
      "x": 3.946089,
      "y": 1.034402,
      "z": -1.33678,
      "visibility": 0.999969
    },
    {
      "x": 3.67183,
      "y": 0.99813,
      "z": 0.080779,
      "visibility": 0.999966
    },
    {
      "x": 3.512159,
      "y": 1.254363,
      "z": -1.3251,
      "visibility": 0.999996
    },
    {
      "x": 3.430321,
      "y": 1.233342,
      "z": -0.912043,
      "visibility": 0.999994
    },
    {
      "x": 4.428279,
      "y": 2.111967,
      "z": -2.147382,
      "visibility": 0.999604
    },
    {
      "x": 3.433183,
      "y": 2.210881,
      "z": 0.664539,
      "visibility": 0.99843
    },
    {
      "x": 4.061773,
      "y": 3.470714,
      "z": -2.539445,
      "visibility": 0.970821
    },
    {
      "x": 2.785509,
      "y": 3.421889,
      "z": 0.692313,
      "visibility": 0.879659
    },
    {
      "x": 3.695468,
      "y": 4.629838,
      "z": -3.190655,
      "visibility": 0.96944
    },
    {
      "x": 1.824073,
      "y": 4.346248,
      "z": -0.595785,
      "visibility": 0.855692
    },
    {
      "x": 3.631556,
      "y": 5.011478,
      "z": -3.579524,
      "visibility": 0.954362
    },
    {
      "x": 1.529685,
      "y": 4.476244,
      "z": -0.761522,
      "visibility": 0.811101
    },
    {
      "x": 3.474292,
      "y": 4.927052,
      "z": -3.736993,
      "visibility": 0.957252
    },
    {
      "x": 1.507757,
      "y": 4.477435,
      "z": -1.216834,
      "visibility": 0.833421
    },
    {
      "x": 3.496579,
      "y": 4.819425,
      "z": -3.238888,
      "visibility": 0.949554
    },
    {
      "x": 1.630309,
      "y": 4.452924,
      "z": -0.827289,
      "visibility": 0.842869
    },
    {
      "x": 4.455247,
      "y": 4.48876,
      "z": -0.737714,
      "visibility": 0.999899
    },
    {
      "x": 3.724047,
      "y": 4.353898,
      "z": 0.736503,
      "visibility": 0.999726
    },
    {
      "x": 4.082671,
      "y": 4.913889,
      "z": -4.687209,
      "visibility": 0.981908
    },
    {
      "x": 2.193238,
      "y": 4.586042,
      "z": -0.80143,
      "visibility": 0.90971
    },
    {
      "x": 3.303949,
      "y": 4.792398,
      "z": -0.85154,
      "visibility": 0.267922
    },
    {
      "x": 3.568657,
      "y": 4.783671,
      "z": -0.092965,
      "visibility": 0.349362
    },
    {
      "x": 3.311387,
      "y": 4.705057,
      "z": -0.361853,
      "visibility": 0.322827
    },
    {
      "x": 3.758139,
      "y": 4.72799,
      "z": 0.067201,
      "visibility": 0.294693
    },
    {
      "x": 2.594397,
      "y": 4.761772,
      "z": -0.222327,
      "visibility": 0.346239
    },
    {
      "x": 4.056131,
      "y": 4.99239,
      "z": -0.200762,
      "visibility": 0.411865
    }
  ]
}