{
  "label": "lotus",
  "landmarks": [
    {
      "x": 2.502592,
      "y": 0.832865,
      "z": -1.355018,
      "visibility": 0.99999
    },
    {
      "x": 2.561276,
      "y": 0.69911,
      "z": -1.158991,
      "visibility": 0.999996
    },
    {
      "x": 2.597403,
      "y": 0.696924,
      "z": -1.159795,
      "visibility": 0.999993
    },
    {
      "x": 2.634062,
      "y": 0.692787,
      "z": -1.160814,
      "visibility": 0.999996
    },
    {
      "x": 2.440897,
      "y": 0.709172,
      "z": -1.183423,
      "visibility": 0.999995
    },
    {
      "x": 2.388467,
      "y": 0.713891,
      "z": -1.183547,
      "visibility": 0.999993
    },
    {
      "x": 2.345348,
      "y": 0.720003,
      "z": -1.183668,
      "visibility": 0.999995
    },
    {
      "x": 2.692293,
      "y": 0.772622,
      "z": -0.192836,
      "visibility": 0.999991
    },
    {
      "x": 2.282786,
      "y": 0.810742,
      "z": -0.304669,
      "visibility": 0.999985
    },
    {
      "x": 2.566903,
      "y": 1.017386,
      "z": -1.019136,
      "visibility": 0.999997
    },
    {
      "x": 2.418199,
      "y": 1.02572,
      "z": -1.04994,
      "visibility": 0.999998
    },
    {
      "x": 3.003587,
      "y": 1.928131,
      "z": -0.176588,
      "visibility": 0.999666
    },
    {
      "x": 2.00359,
      "y": 1.925558,
      "z": -0.169137,
      "visibility": 0.999305
    },
    {
      "x": 3.135955,
      "y": 3.240131,
      "z": -0.352615,
      "visibility": 0.936176
    },
    {
      "x": 1.911318,
      "y": 3.260717,
      "z": -0.308198,
      "visibility": 0.92826
    },
    {
      "x": 3.545669,
      "y": 4.115101,
      "z": -1.521332,
      "visibility": 0.843863
    },
    {
      "x": 1.415834,
      "y": 4.120649,
      "z": -1.658286,
      "visibility": 0.880586
    },
    {
      "x": 3.711788,
      "y": 4.285737,
      "z": -1.72944,
      "visibility": 0.840144
    },
    {
      "x": 1.276438,
      "y": 4.301919,
      "z": -1.861373,
      "visibility": 0.894414
    },
    {
      "x": 3.738054,
      "y": 4.273371,
      "z": -2.054306,
      "visibility": 0.859601
    },
    {
      "x": 1.268155,
      "y": 4.244876,
      "z": -2.213358,
      "visibility": 0.912217
    },
    {
      "x": 3.665033,
      "y": 4.241135,
      "z": -1.672524,
      "visibility": 0.872077
    },
    {
      "x": 1.32215,
      "y": 4.196058,
      "z": -1.822202,
      "visibility": 0.918401
    },
    {
      "x": 2.802508,
      "y": 4.143337,
      "z": -0.026183,
      "visibility": 0.99984
    },
    {
      "x": 2.173821,
      "y": 4.090146,
      "z": 0.025849,
      "visibility": 0.999697
    },
    {
      "x": 3.597811,
      "y": 4.734308,
      "z": -2.478859,
      "visibility": 0.995087
    },
    {
      "x": 1.338136,
      "y": 4.670718,
      "z": -2.205861,
      "visibility": 0.985695
    },
    {
      "x": 2.310358,
      "y": 4.412802,
      "z": -0.687716,
      "visibility": 0.673495
    },
    {
      "x": 2.488302,
      "y": 4.480616,
      "z": -0.523072,
      "visibility": 0.498044
    },
    {
      "x": 2.260735,
      "y": 4.165067,
      "z": -0.421774,
      "visibility": 0.559008
    },
    {
      "x": 2.551669,
      "y": 4.302296,
      "z": -0.264182,
      "visibility": 0.401604
    },
    {
      "x": 1.797821,
      "y": 4.354161,
      "z": -0.619109,
      "visibility": 0.617122
    },
    {
      "x": 2.947198,
      "y": 4.491641,
      "z": -0.44195,
      "visibility": 0.463861
    }
  ]
}