{
  "label": "low_lunge",
  "landmarks": [
    {
      "x": 12.653592,
      "y": 5.679412,
      "z": -5.354959,
      "visibility": 0.999979
    },
    {
      "x": 12.915947,
      "y": 6.191882,
      "z": -6.157661,
      "visibility": 0.999993
    },
    {
      "x": 12.88635,
      "y": 6.297648,
      "z": -6.156464,
      "visibility": 0.999994
    },
    {
      "x": 12.852087,
      "y": 6.415083,
      "z": -6.162513,
      "visibility": 0.999992
    },
    {
      "x": 12.935556,
      "y": 6.15411,
      "z": -4.737268,
      "visibility": 0.999981
    },
    {
      "x": 12.927276,
      "y": 6.230981,
      "z": -4.739809,
      "visibility": 0.999984
    },
    {
      "x": 12.920211,
      "y": 6.318936,
      "z": -4.739068,
      "visibility": 0.999986
    },
    {
      "x": 12.388456,
      "y": 7.152387,
      "z": -8.405776,
      "visibility": 0.99999
    },
    {
      "x": 12.556901,
      "y": 7.130506,
      "z": -2.077222,
      "visibility": 0.99999
    },
    {
      "x": 12.078941,
      "y": 5.899674,
      "z": -6.131733,
      "visibility": 0.999797
    },
    {
      "x": 12.160953,
      "y": 5.860563,
      "z": -4.316727,
      "visibility": 0.999886
    },
    {
      "x": 10.071998,
      "y": 7.631388,
      "z": -10.226158,
      "visibility": 0.999891
    },
    {
      "x": 10.768721,
      "y": 8.348728,
      "z": 1.04098,
      "visibility": 0.999458
    },
    {
      "x": 12.446668,
      "y": 3.505787,
      "z": -14.052731,
      "visibility": 0.995682
    },
    {
      "x": 12.666877,
      "y": 4.25183,
      "z": 1.361569,
      "visibility": 0.195421
    },
    {
      "x": 15.763922,
      "y": 1.407572,
      "z": -16.143271,
      "visibility": 0.981598
    },
    {
      "x": 15.65584,
      "y": 2.173585,
      "z": -0.295379,
      "visibility": 0.333848
    },
    {
      "x": 16.583874,
      "y": 1.090702,
      "z": -18.229466,
      "visibility": 0.959676
    },
    {
      "x": 16.618389,
      "y": 1.907065,
      "z": -0.735715,
      "visibility": 0.312341
    },
    {
      "x": 16.779629,
      "y": 1.349431,
      "z": -17.776175,
      "visibility": 0.95401
    },
    {
      "x": 16.757956,
      "y": 1.962588,
      "z": -1.024942,
      "visibility": 0.310633
    },
    {
      "x": 16.566154,
      "y": 1.441511,
      "z": -16.111353,
      "visibility": 0.938873
    },
    {
      "x": 16.467608,
      "y": 2.065772,
      "z": -0.599688,
      "visibility": 0.313174
    },
    {
      "x": 6.704595,
      "y": 15.653872,
      "z": -3.703999,
      "visibility": 0.999971
    },
    {
      "x": 8.321089,
      "y": 15.909907,
      "z": 3.688564,
      "visibility": 0.99998
    },
    {
      "x": 1.31589,
      "y": 13.419364,
      "z": -3.649684,
      "visibility": 0.999792
    },
    {
      "x": 13.410175,
      "y": 20.123616,
      "z": 4.472864,
      "visibility": 0.983228
    },
    {
      "x": 1.763553,
      "y": 20.054356,
      "z": -1.206134,
      "visibility": 0.966321
    },
    {
      "x": 19.271069,
      "y": 19.995275,
      "z": 1.128775,
      "visibility": 0.984777
    },
    {
      "x": 2.454836,
      "y": 20.907679,
      "z": -0.711258,
      "visibility": 0.968234
    },
    {
      "x": 19.773452,
      "y": 19.730114,
      "z": 0.885562,
      "visibility": 0.979553
    },
    {
      "x": 0.484651,
      "y": 20.633124,
      "z": -0.079529,
      "visibility": 0.938702
    },
    {
      "x": 22.272214,
      "y": 20.790218,
      "z": -0.033501,
      "visibility": 0.972493
    }
  ]
}