{
  "label": "low_lunge",
  "landmarks": [
    {
      "x": 30.767363,
      "y": 15.931198,
      "z": -14.411976,
      "visibility": 0.999862
    },
    {
      "x": 31.088821,
      "y": 17.173767,
      "z": -16.132657,
      "visibility": 0.999818
    },
    {
      "x": 31.039038,
      "y": 17.343168,
      "z": -16.126907,
      "visibility": 0.999818
    },
    {
      "x": 30.987712,
      "y": 17.529403,
      "z": -16.125172,
      "visibility": 0.999782
    },
    {
      "x": 31.06044,
      "y": 17.115365,
      "z": -13.667458,
      "visibility": 0.999837
    },
    {
      "x": 30.997232,
      "y": 17.236112,
      "z": -13.658019,
      "visibility": 0.999808
    },
    {
      "x": 30.933798,
      "y": 17.365,
      "z": -13.646668,
      "visibility": 0.999825
    },
    {
      "x": 30.094728,
      "y": 18.821793,
      "z": -20.066683,
      "visibility": 0.999781
    },
    {
      "x": 30.155235,
      "y": 18.726556,
      "z": -8.355083,
      "visibility": 0.999888
    },
    {
      "x": 29.979636,
      "y": 16.072387,
      "z": -15.793734,
      "visibility": 0.999383
    },
    {
      "x": 30.015108,
      "y": 16.077513,
      "z": -12.389885,
      "visibility": 0.99963
    },
    {
      "x": 27.017312,
      "y": 18.8695,
      "z": -22.406445,
      "visibility": 0.999918
    },
    {
      "x": 26.925604,
      "y": 19.865286,
      "z": -2.680405,
      "visibility": 0.999864
    },
    {
      "x": 32.108115,
      "y": 11.385862,
      "z": -27.742845,
      "visibility": 0.998175
    },
    {
      "x": 32.072324,
      "y": 13.20542,
      "z": -1.637311,
      "visibility": 0.31906
    },
    {
      "x": 37.477687,
      "y": 10.27944,
      "z": -30.208087,
      "visibility": 0.986276
    },
    {
      "x": 37.265146,
      "y": 11.118506,
      "z": -7.796455,
      "visibility": 0.421544
    },
    {
      "x": 38.726752,
      "y": 11.483282,
      "z": -33.897876,
      "visibility": 0.964042
    },
    {
      "x": 38.560729,
      "y": 12.770931,
      "z": -8.749523,
      "visibility": 0.432258
    },
    {
      "x": 38.847407,
      "y": 12.431312,
      "z": -33.128062,
      "visibility": 0.954746
    },
    {
      "x": 38.681957,
      "y": 13.428516,
      "z": -9.702586,
      "visibility": 0.443347
    },
    {
      "x": 38.390976,
      "y": 12.263337,
      "z": -30.220219,
      "visibility": 0.941986
    },
    {
      "x": 38.271242,
      "y": 13.197235,
      "z": -8.572621,
      "visibility": 0.465891
    },
    {
      "x": 23.155754,
      "y": 38.241973,
      "z": -7.566688,
      "visibility": 0.999837
    },
    {
      "x": 21.220283,
      "y": 36.632079,
      "z": 7.553437,
      "visibility": 0.99998
    },
    {
      "x": 30.181163,
      "y": 48.560273,
      "z": -14.71525,
      "visibility": 0.999531
    },
    {
      "x": 13.287051,
      "y": 30.66662,
      "z": 7.315653,
      "visibility": 0.995412
    },
    {
      "x": 41.326781,
      "y": 45.11028,
      "z": -7.726794,
      "visibility": 0.989233
    },
    {
      "x": 11.880987,
      "y": 44.976515,
      "z": 15.125381,
      "visibility": 0.996098
    },
    {
      "x": 42.831235,
      "y": 43.75143,
      "z": -6.691071,
      "visibility": 0.986719
    },
    {
      "x": 12.567118,
      "y": 47.668182,
      "z": 15.722154,
      "visibility": 0.995266
    },
    {
      "x": 42.264283,
      "y": 49.696824,
      "z": -6.872858,
      "visibility": 0.986933
    },
    {
      "x": 7.574245,
      "y": 47.782848,
      "z": 14.844892,
      "visibility": 0.989989
    }
  ]
}