{
  "label": "plank",
  "landmarks": [
    {
      "x": 3.021056,
      "y": 9.655736,
      "z": 1.059788,
      "visibility": 0.999981
    },
    {
      "x": 2.730222,
      "y": 9.006339,
      "z": 0.245313,
      "visibility": 0.999976
    },
    {
      "x": 2.741284,
      "y": 8.898166,
      "z": 0.243772,
      "visibility": 0.999972
    },
    {
      "x": 2.749136,
      "y": 8.779412,
      "z": 0.245478,
      "visibility": 0.999979
    },
    {
      "x": 2.731621,
      "y": 9.029966,
      "z": 1.526793,
      "visibility": 0.999973
    },
    {
      "x": 2.74618,
      "y": 8.951873,
      "z": 1.526567,
      "visibility": 0.999967
    },
    {
      "x": 2.756589,
      "y": 8.863304,
      "z": 1.527736,
      "visibility": 0.999981
    },
    {
      "x": 3.074203,
      "y": 7.960068,
      "z": -1.574335,
      "visibility": 0.999957
    },
    {
      "x": 3.100226,
      "y": 8.029524,
      "z": 4.07077,
      "visibility": 0.999955
    },
    {
      "x": 3.491707,
      "y": 9.507906,
      "z": 0.519914,
      "visibility": 0.999938
    },
    {
      "x": 3.521089,
      "y": 9.572258,
      "z": 2.178753,
      "visibility": 0.999906
    },
    {
      "x": 5.119417,
      "y": 8.648043,
      "z": -5.226229,
      "visibility": 0.999949
    },
    {
      "x": 6.072341,
      "y": 8.344834,
      "z": 8.195969,
      "visibility": 0.999654
    },
    {
      "x": 4.802243,
      "y": 14.971118,
      "z": -7.598024,
      "visibility": 0.99589
    },
    {
      "x": 6.311083,
      "y": 13.964748,
      "z": 9.197354,
      "visibility": 0.729044
    },
    {
      "x": 5.047048,
      "y": 20.405749,
      "z": -7.537119,
      "visibility": 0.994314
    },
    {
      "x": 6.27589,
      "y": 18.993982,
      "z": 6.635558,
      "visibility": 0.847217
    },
    {
      "x": 4.277605,
      "y": 20.983074,
      "z": -9.190204,
      "visibility": 0.988508
    },
    {
      "x": 5.594331,
      "y": 19.104574,
      "z": 6.927841,
      "visibility": 0.779465
    },
    {
      "x": 4.242078,
      "y": 20.723084,
      "z": -7.999969,
      "visibility": 0.986117
    },
    {
      "x": 5.502842,
      "y": 19.290647,
      "z": 5.352145,
      "visibility": 0.782538
    },
    {
      "x": 4.636775,
      "y": 20.475163,
      "z": -7.091561,
      "visibility": 0.979144
    },
    {
      "x": 5.721361,
      "y": 19.348245,
      "z": 5.900429,
      "visibility": 0.793163
    },
    {
      "x": 11.091033,
      "y": 10.312339,
      "z": -4.182386,
      "visibility": 0.99956
    },
    {
      "x": 11.337885,
      "y": 9.904919,
      "z": 4.180695,
      "visibility": 0.999155
    },
    {
      "x": 15.909645,
      "y": 13.883048,
      "z": -5.024872,
      "visibility": 0.956575
    },
    {
      "x": 15.9868,
      "y": 13.586609,
      "z": 3.83327,
      "visibility": 0.326877
    },
    {
      "x": 21.083587,
      "y": 17.888238,
      "z": -4.667847,
      "visibility": 0.976109
    },
    {
      "x": 20.724377,
      "y": 17.436138,
      "z": 4.231944,
      "visibility": 0.732989
    },
    {
      "x": 22.198042,
      "y": 18.23091,
      "z": -4.809088,
      "visibility": 0.975371
    },
    {
      "x": 21.916438,
      "y": 17.735621,
      "z": 4.150413,
      "visibility": 0.819401
    },
    {
      "x": 20.11971,
      "y": 21.053515,
      "z": -8.031561,
      "visibility": 0.97335
    },
    {
      "x": 20.008178,
      "y": 20.751551,
      "z": 1.335226,
      "visibility": 0.852791
    }
  ]
}