{
  "label": "tree",
  "landmarks": [
    {
      "x": 9.405224,
      "y": 5.337565,
      "z": -2.869387,
      "visibility": 0.995658
    },
    {
      "x": 9.460042,
      "y": 5.096779,
      "z": -2.488948,
      "visibility": 0.995125
    },
    {
      "x": 9.503196,
      "y": 5.095658,
      "z": -2.488848,
      "visibility": 0.992109
    },
    {
      "x": 9.550063,
      "y": 5.095603,
      "z": -2.49045,
      "visibility": 0.993601
    },
    {
      "x": 9.322025,
      "y": 5.088971,
      "z": -2.577226,
      "visibility": 0.995956
    },
    {
      "x": 9.271284,
      "y": 5.079778,
      "z": -2.577546,
      "visibility": 0.993748
    },
    {
      "x": 9.227683,
      "y": 5.072385,
      "z": -2.578156,
      "visibility": 0.995087
    },
    {
      "x": 9.609379,
      "y": 5.218793,
      "z": -0.700017,
      "visibility": 0.9962
    },
    {
      "x": 9.151402,
      "y": 5.219953,
      "z": -1.056211,
      "visibility": 0.99405
    },
    {
      "x": 9.493122,
      "y": 5.613989,
      "z": -2.207027,
      "visibility": 0.992552
    },
    {
      "x": 9.308271,
      "y": 5.594955,
      "z": -2.31461,
      "visibility": 0.994646
    },
    {
      "x": 9.888963,
      "y": 6.495047,
      "z": -0.124996,
      "visibility": 0.989037
    },
    {
      "x": 8.890018,
      "y": 6.449126,
      "z": -1.423634,
      "visibility": 0.998158
    },
    {
      "x": 9.822809,
      "y": 4.160911,
      "z": -0.673998,
      "visibility": 0.961247
    },
    {
      "x": 9.021286,
      "y": 4.171986,
      "z": -2.995809,
      "visibility": 0.983424
    },
    {
      "x": 9.54087,
      "y": 2.098815,
      "z": -1.180578,
      "visibility": 0.935549
    },
    {
      "x": 9.306977,
      "y": 2.226516,
      "z": -3.253438,
      "visibility": 0.971198
    },
    {
      "x": 9.483996,
      "y": 1.643468,
      "z": -1.517896,
      "visibility": 0.880956
    },
    {
      "x": 9.37442,
      "y": 1.738407,
      "z": -3.757531,
      "visibility": 0.934135
    },
    {
      "x": 9.464269,
      "y": 1.57083,
      "z": -1.503251,
      "visibility": 0.867395
    },
    {
      "x": 9.351679,
      "y": 1.69835,
      "z": -3.582106,
      "visibility": 0.925507
    },
    {
      "x": 9.474503,
      "y": 1.756157,
      "z": -1.255764,
      "visibility": 0.867375
    },
    {
      "x": 9.340313,
      "y": 1.867502,
      "z": -3.268831,
      "visibility": 0.920211
    },
    {
      "x": 9.851623,
      "y": 10.717316,
      "z": 0.485037,
      "visibility": 0.999399
    },
    {
      "x": 9.195563,
      "y": 11.040371,
      "z": -0.484354,
      "visibility": 0.999713
    },
    {
      "x": 11.286444,
      "y": 12.486391,
      "z": -0.755881,
      "visibility": 0.95738
    },
    {
      "x": 9.363878,
      "y": 14.390466,
      "z": -0.601117,
      "visibility": 0.956234
    },
    {
      "x": 9.811536,
      "y": 12.649167,
      "z": 3.292965,
      "visibility": 0.675381
    },
    {
      "x": 9.624874,
      "y": 17.40902,
      "z": 2.217111,
      "visibility": 0.979269
    },
    {
      "x": 9.572376,
      "y": 12.330659,
      "z": 3.69448,
      "visibility": 0.743812
    },
    {
      "x": 9.708814,
      "y": 17.772505,
      "z": 2.419906,
      "visibility": 0.943084
    },
    {
      "x": 9.467022,
      "y": 13.958963,
      "z": 3.137284,
      "visibility": 0.646324
    },
    {
      "x": 9.504548,
      "y": 17.999589,
      "z": 0.840422,
      "visibility": 0.953682
    }
  ]
}