{
  "label": "warrior_two",
  "landmarks": [
    {
      "x": 7.099059,
      "y": 3.369615,
      "z": -0.899239,
      "visibility": 0.999973
    },
    {
      "x": 7.285768,
      "y": 3.221734,
      "z": -0.916802,
      "visibility": 0.999977
    },
    {
      "x": 7.335862,
      "y": 3.241931,
      "z": -0.917254,
      "visibility": 0.999976
    },
    {
      "x": 7.367818,
      "y": 3.25975,
      "z": -0.919155,
      "visibility": 0.999979
    },
    {
      "x": 7.260292,
      "y": 3.191977,
      "z": -0.639382,
      "visibility": 0.999972
    },
    {
      "x": 7.271652,
      "y": 3.192142,
      "z": -0.640512,
      "visibility": 0.99997
    },
    {
      "x": 7.282504,
      "y": 3.195872,
      "z": -0.640145,
      "visibility": 0.999976
    },
    {
      "x": 7.517457,
      "y": 3.415548,
      "z": -0.558934,
      "visibility": 0.999973
    },
    {
      "x": 7.415353,
      "y": 3.370563,
      "z": 0.686333,
      "visibility": 0.999973
    },
    {
      "x": 7.146737,
      "y": 3.651758,
      "z": -0.724055,
      "visibility": 0.999926
    },
    {
      "x": 7.099929,
      "y": 3.608166,
      "z": -0.366776,
      "visibility": 0.999885
    },
    {
      "x": 7.902544,
      "y": 4.895993,
      "z": -0.812588,
      "visibility": 0.99995
    },
    {
      "x": 6.998607,
      "y": 4.468327,
      "z": 1.630267,
      "visibility": 0.999975
    },
    {
      "x": 9.206005,
      "y": 5.941036,
      "z": -1.570736,
      "visibility": 0.978556
    },
    {
      "x": 5.971767,
      "y": 4.821227,
      "z": 1.498277,
      "visibility": 0.972664
    },
    {
      "x": 10.672955,
      "y": 6.67454,
      "z": -2.809427,
      "visibility": 0.853983
    },
    {
      "x": 5.316125,
      "y": 4.941999,
      "z": -0.388512,
      "visibility": 0.941302
    },
    {
      "x": 10.633588,
      "y": 7.012273,
      "z": -3.291756,
      "visibility": 0.763042
    },
    {
      "x": 5.074626,
      "y": 4.916567,
      "z": -0.848728,
      "visibility": 0.874546
    },
    {
      "x": 10.695579,
      "y": 6.858524,
      "z": -3.775456,
      "visibility": 0.788926
    },
    {
      "x": 5.110818,
      "y": 4.780915,
      "z": -1.290513,
      "visibility": 0.887991
    },
    {
      "x": 10.58649,
      "y": 6.895055,
      "z": -3.086465,
      "visibility": 0.796529
    },
    {
      "x": 5.177107,
      "y": 4.883548,
      "z": -0.684658,
      "visibility": 0.897081
    },
    {
      "x": 7.531399,
      "y": 8.437928,
      "z": -1.603031,
      "visibility": 0.99964
    },
    {
      "x": 7.595915,
      "y": 8.359906,
      "z": 1.603725,
      "visibility": 0.999879
    },
    {
      "x": 6.803184,
      "y": 10.415255,
      "z": -2.187461,
      "visibility": 0.998434
    },
    {
      "x": 7.734991,
      "y": 9.131459,
      "z": 0.640713,
      "visibility": 0.964258
    },
    {
      "x": 8.511307,
      "y": 12.386674,
      "z": -1.013756,
      "visibility": 0.997358
    },
    {
      "x": 8.757458,
      "y": 11.696205,
      "z": 1.153255,
      "visibility": 0.962311
    },
    {
      "x": 9.048075,
      "y": 12.640326,
      "z": -0.872874,
      "visibility": 0.990755
    },
    {
      "x": 9.112902,
      "y": 12.116157,
      "z": 1.18744,
      "visibility": 0.928292
    },
    {
      "x": 8.117538,
      "y": 13.082463,
      "z": -1.844552,
      "visibility": 0.992947
    },
    {
      "x": 8.346905,
      "y": 12.328832,
      "z": 0.360584,
      "visibility": 0.947059
    }
  ]
}